LICENSE
MANIFEST.in
README.md
requirements.txt
setup.cfg
setup.py
geographica_longitude_async.egg-info/PKG-INFO
geographica_longitude_async.egg-info/SOURCES.txt
geographica_longitude_async.egg-info/dependency_links.txt
geographica_longitude_async.egg-info/entry_points.txt
geographica_longitude_async.egg-info/requires.txt
geographica_longitude_async.egg-info/top_level.txt
longitude/__init__.py
longitude/config.py
longitude/exceptions.py
longitude/mail.py
longitude/response.py
longitude/rest.py
longitude/scheduler.py
longitude/utils.py
longitude/validators.py
longitude/auth/__init__.py
longitude/auth/microsoft.py
longitude/auth/models.py
longitude/auth/migrations/20180322_1313_e93ef06edae1_generate_user_model.py
longitude/auth/migrations/20180322_1351_cea8fff92651_insert_public_pgp_key_in_db.py
longitude/auth/migrations/20180322_1732_e6cde76060e7_user_token_table.py
longitude/auth/migrations/20180323_1420_a84311174ef7_rename_auth_columns.py
longitude/auth/migrations/20180723_1148_c8c47e8d607a_delete_cascade_user_token.py
longitude/auth/migrations/__init__.py
longitude/credential/__init__.py
longitude/credential/model.py
longitude/credential/routes.py
longitude/credential/migrations/20180320_1818_c6a61e3cc7ec_init_credentials.py
longitude/credential/migrations/20180323_1357_987654c999b7_add_field_name_to_credential.py
longitude/credential/migrations/__init__.py
longitude/migration/__init__.py
longitude/migration/command.py
longitude/migration/env.py
longitude/models/__init__.py
longitude/models/postgresqlmodel.py
longitude/models/sql.py
longitude/permission/__init__.py
longitude/permission/models.py
longitude/permission/migrations/20180619_1421_3f4ec3873142_role_support.py
longitude/permission/migrations/20180801_1640_644f2887df07_rename_is_superadmin_to_is_admin.py
longitude/permission/migrations/__init__.py
longitude/schemas/__init__.py
longitude/schemas/fields.py