Metadata-Version: 1.1
Name: geographica-longitude-async
Version: 0.3.46
Summary: Longitude
Home-page: https://github.com/GeographicaGS/Longitude-async
Author: Geographica
Author-email: pypi@geographica.gs
License: MIT
Keywords: carto longitude alembic async sanic jwt
Platform: UNKNOWN
Classifier: Development Status :: 3 - Alpha
Classifier: Intended Audience :: Developers
Classifier: Topic :: Software Development :: Build Tools
Classifier: License :: OSI Approved :: MIT License
Classifier: Programming Language :: Python :: 3
Classifier: Programming Language :: Python :: 3.3
Classifier: Programming Language :: Python :: 3.4
Classifier: Programming Language :: Python :: 3.5
Classifier: Programming Language :: Python :: 3.6
